{"content":[{"id":"43642543","settings":{"padding":{"unit":"px","top":"100","right":"0","bottom":"100","left":"0","isLinked":false}},"elements":[{"id":"118d022d","settings":{"title":"404 Not Found ","header_size":"h3","align":"center"},"elements":[],"isInner":false,"widgetType":"heading","elType":"widget"},{"id":"24fbe581","settings":{"text":"Go to Homepage","align":"center","typography_typography":"custom","typography_font_family":"Poppins","border_border":"solid","border_width":{"unit":"px","top":"1","right":"1","bottom":"1","left":"1","isLinked":true},"__globals__":{"background_color":"globals\/colors?id=primary","button_text_color":"globals\/colors?id=secondary","border_color":"globals\/colors?id=primary","button_hover_border_color":"globals\/colors?id=primary","button_background_hover_color":"globals\/colors?id=secondary","hover_color":"globals\/colors?id=primary"},"__dynamic__":{"link":"[elementor-tag id=\"924b911\" name=\"site-url\" settings=\"%7B%7D\"]"}},"elements":[],"isInner":false,"widgetType":"button","elType":"widget"}],"isInner":false,"elType":"container"}],"settings":[],"metadata":[]}